multihash/__init__.py
multihash/__init__.pyi
multihash/multicodec.py
multihash/multicodec.pyi
multihash/py.typed
multi_hash-0.1.0.dist-info/LICENSE.MIT
multi_hash-0.1.0.dist-info/METADATA
multi_hash-0.1.0.dist-info/WHEEL
multi_hash-0.1.0.dist-info/top_level.txt
multi_hash-0.1.0.dist-info/RECORD
